scrapy_zstd/__init__.py
scrapy_zstd/postprocessing.py
scrapy_zstd-0.2.0.dist-info/METADATA
scrapy_zstd-0.2.0.dist-info/WHEEL
scrapy_zstd-0.2.0.dist-info/licenses/LICENSE.txt
scrapy_zstd-0.2.0.dist-info/RECORD
