Metadata-Version: 2.4
Name: scrapy-zstd
Version: 0.2.0
Summary: A Scrapy plugin to compress feeds with Zstandard (zstd).
Project-URL: Homepage, https://github.com/takebayashi/scrapy-zstd
Author: Shun Takebayashi
License-Expression: MIT
License-File: LICENSE.txt
Classifier: Framework :: Scrapy
Requires-Python: >=3.9
Requires-Dist: zstandard
